redd_harvest/__init__.py
redd_harvest/config.py
redd_harvest/fetch.py
redd_harvest/harvest.py
redd_harvest/post.py
redd_harvest/version.py
redd_harvest-0.0.1.dist-info/LICENSE
redd_harvest-0.0.1.dist-info/METADATA
redd_harvest-0.0.1.dist-info/WHEEL
redd_harvest-0.0.1.dist-info/entry_points.txt
redd_harvest-0.0.1.dist-info/top_level.txt
redd_harvest-0.0.1.dist-info/RECORD
