Metadata-Version: 2.1
Name: redd-harvest
Version: 0.0.1
Summary: Download media from Reddit posts.
Home-page: https://github.com/pyqlsa/redd-harvest
Author: pyqlsa
License: MIT
Keywords: reddit,download
Classifier: Development Status :: 3 - Alpha
Classifier: Environment :: Console
Classifier: Topic :: Utilities
Classifier: License :: OSI Approved :: MIT License
Classifier: Programming Language :: Python :: 3
Requires-Python: >=3.10
License-File: LICENSE
Requires-Dist: click ==8.1.7
Requires-Dist: filetype ==1.2.0
Requires-Dist: praw ==7.7.1
Requires-Dist: PyYaml ==6.0.1
Requires-Dist: requests ==2.32.3
Requires-Dist: tqdm ==4.66.4
